torchkeras/__init__.py
torchkeras/data.py
torchkeras/eda.py
torchkeras/email.py
torchkeras/hugmodel.py
torchkeras/kerascallbacks.py
torchkeras/kerasmodel.py
torchkeras/metrics.py
torchkeras/pbar.py
torchkeras/plots.py
torchkeras/soup.py
torchkeras/stacker.py
torchkeras/summary.py
torchkeras/utils.py
torchkeras/vlog.py
torchkeras/assets/SimHei.ttf
torchkeras/assets/park.jpg
torchkeras/assets/zidane.jpg
torchkeras/chat/__init__.py
torchkeras/chat/chatgpt.py
torchkeras/chat/chatllm.py
torchkeras/chat/ollama.py
torchkeras/tabular/__init__.py
torchkeras/tabular/step_runner.py
torchkeras/tabular/tabular_dataset.py
torchkeras/tabular/tabular_preprocess.py
torchkeras/tabular/config/__init__.py
torchkeras/tabular/config/config.py
torchkeras/tabular/models/__init__.py
torchkeras/tabular/models/base_model.py
torchkeras/tabular/models/autoint/__init__.py
torchkeras/tabular/models/autoint/autoint.py
torchkeras/tabular/models/autoint/config.py
torchkeras/tabular/models/category_embedding/__init__.py
torchkeras/tabular/models/category_embedding/category_embedding_model.py
torchkeras/tabular/models/category_embedding/config.py
torchkeras/tabular/models/common/__init__.py
torchkeras/tabular/models/common/heads/__init__.py
torchkeras/tabular/models/common/heads/blocks.py
torchkeras/tabular/models/common/heads/config.py
torchkeras/tabular/models/common/layers/__init__.py
torchkeras/tabular/models/common/layers/activations.py
torchkeras/tabular/models/common/layers/batch_norm.py
torchkeras/tabular/models/common/layers/embeddings.py
torchkeras/tabular/models/common/layers/gated_units.py
torchkeras/tabular/models/common/layers/misc.py
torchkeras/tabular/models/common/layers/soft_trees.py
torchkeras/tabular/models/common/layers/transformers.py
torchkeras/tabular/models/danet/__init__.py
torchkeras/tabular/models/danet/arch_blocks.py
torchkeras/tabular/models/danet/config.py
torchkeras/tabular/models/danet/danet.py
torchkeras/tabular/models/deepcross/__init__.py
torchkeras-4.0.5.dist-info/licenses/LICENSE
torchkeras-4.0.5.dist-info/METADATA
torchkeras-4.0.5.dist-info/WHEEL
torchkeras-4.0.5.dist-info/top_level.txt
torchkeras-4.0.5.dist-info/RECORD
