Metadata-Version: 2.4
Name: torchkeras
Version: 4.0.5
Summary: pytorch❤️keras
Home-page: https://github.com/lyhue1991/torchkeras
Author: lyhue1991,octopus,Laugh
Author-email: lyhue1991@163.com
License: MIT
Keywords: vlog,deep-learning,DL,pytorch,torch,keras
Classifier: Programming Language :: Python :: 3
Classifier: License :: OSI Approved :: MIT License
Classifier: Operating System :: OS Independent
Requires-Python: >=3.5
License-File: LICENSE
Dynamic: author
Dynamic: author-email
Dynamic: classifier
Dynamic: description
Dynamic: description-content-type
Dynamic: home-page
Dynamic: keywords
Dynamic: license
Dynamic: license-file
Dynamic: requires-python
Dynamic: summary
